searchtweets/__init__.py
searchtweets/_version.py
searchtweets/api_utils.py
searchtweets/credentials.py
searchtweets/result_stream.py
searchtweets/utils.py
searchtweets_v2-1.1.1.data/scripts/poll_tweets.py
searchtweets_v2-1.1.1.data/scripts/search_tweets.py
searchtweets_v2-1.1.1.dist-info/LICENSE
searchtweets_v2-1.1.1.dist-info/METADATA
searchtweets_v2-1.1.1.dist-info/WHEEL
searchtweets_v2-1.1.1.dist-info/top_level.txt
searchtweets_v2-1.1.1.dist-info/RECORD
