Metadata-Version: 2.1
Name: searchtweets-v2
Version: 1.1.1
Summary: Wrapper for Twitter API v2 search endpoints (both 'search Tweets' and 'count Tweets' endpoints).
Home-page: https://github.com/twitterdev/search-tweets-python
Author: Fiona Pigott, Jeff Kolb, Josh Montague, Aaron Gonzales, Jim Moffitt
Author-email: dev-support@twitter.com
License: MIT
Platform: UNKNOWN
Requires-Python: >=3.3
Requires-Dist: requests
Requires-Dist: pyyaml
Requires-Dist: python-dateutil
